b_cfn_sagemaker_endpoint/__init__.py
b_cfn_sagemaker_endpoint/bucket_event.py
b_cfn_sagemaker_endpoint/model_props.py
b_cfn_sagemaker_endpoint/resource.py
b_cfn_sagemaker_endpoint/refresh/__init__.py
b_cfn_sagemaker_endpoint/refresh/function.py
b_cfn_sagemaker_endpoint/refresh/source/__init__.py
b_cfn_sagemaker_endpoint/refresh/source/index.py
b_cfn_sagemaker_endpoint-0.0.4.dist-info/LICENSE
b_cfn_sagemaker_endpoint-0.0.4.dist-info/METADATA
b_cfn_sagemaker_endpoint-0.0.4.dist-info/WHEEL
b_cfn_sagemaker_endpoint-0.0.4.dist-info/top_level.txt
b_cfn_sagemaker_endpoint-0.0.4.dist-info/RECORD
