Metadata-Version: 2.1
Name: b-cfn-sagemaker-endpoint
Version: 0.0.4
Summary: AWS CloudFormation resource that handles the deployment and updates of SageMaker models endpoint.
Home-page: https://github.com/Biomapas/B.CfnSagemakerEndpoint
Author: Matas Gumbinas
Author-email: matas.gumbinas@biomapas.com
License: Apache License 2.0
Keywords: aws cdk sagemaker sagemaker-endpoint sagemaker-deployment python
Platform: UNKNOWN
Classifier: Programming Language :: Python :: 3
Classifier: Operating System :: OS Independent
Requires-Dist: aws-cdk.aws-iam (<2.0.0,>=1.90.0)
Requires-Dist: aws-cdk.aws-lambda (<2.0.0,>=1.90.0)
Requires-Dist: aws-cdk.aws-sagemaker (<2.0.0,>=1.90.0)
Requires-Dist: aws-cdk.aws-ssm (<2.0.0,>=1.90.0)
Requires-Dist: aws-cdk.aws-s3 (<2.0.0,>=1.90.0)
Requires-Dist: aws-cdk.aws-s3-assets (<2.0.0,>=1.90.0)
Requires-Dist: aws-cdk.aws-s3-notifications (<2.0.0,>=1.90.0)
Requires-Dist: aws-cdk.core (<2.0.0,>=1.90.0)
Requires-Dist: b-aws-cdk-parallel (<3.0.0,>=2.2.0)
Requires-Dist: b-aws-testing-framework (<2.0.0,>=0.6.0)
Requires-Dist: b-cfn-s3-large-deployment (<2.0.0,>=1.1.2)
Requires-Dist: boto3 (>=1.18.32<2.0.0)
Requires-Dist: urllib3 (<2.0.0,>=1.26.6)
